perforatedai/pb_models.cpython-36m-x86_64-linux-gnu.so
perforatedai/check_license.cpython-36m-x86_64-linux-gnu.so
perforatedai/__init__.cpython-36m-x86_64-linux-gnu.so
perforatedai/pb_layer.cpython-36m-x86_64-linux-gnu.so
perforatedai/pb_utils.cpython-36m-x86_64-linux-gnu.so
perforatedai/blockwisePB.cpython-36m-x86_64-linux-gnu.so
perforatedai/pb_neuron_layer_tracker.cpython-36m-x86_64-linux-gnu.so
perforatedai/cleanLoad.cpython-36m-x86_64-linux-gnu.so
perforatedai/globalsFile.cpython-36m-x86_64-linux-gnu.so
perforatedai_freemium-1.0.0.dist-info/top_level.txt
perforatedai_freemium-1.0.0.dist-info/WHEEL
perforatedai_freemium-1.0.0.dist-info/RECORD
perforatedai_freemium-1.0.0.dist-info/METADATA
