Metadata-Version: 2.1
Name: perforatedai-freemium
Version: 1.0.0
Summary: perforatedai premium
Home-page: UNKNOWN
Author: PerforatedAI
Author-email: rorry@perforatedai.com
License: This software may only be used by getting a license from PerforatedAI.com and agreeing to the terms and conditions
Platform: UNKNOWN
Requires-Python: >=3.6
Requires-Dist: torch
Requires-Dist: torchvision
Requires-Dist: matplotlib
Requires-Dist: pandas
Requires-Dist: rsa
Requires-Dist: pyyaml
